odoo8_addon_l10n_fr_chorus_ubl-8.0.1.0.0.99.dev3-py2.7-nspkg.pth
odoo8_addon_l10n_fr_chorus_ubl-8.0.1.0.0.99.dev3.dist-info/METADATA
odoo8_addon_l10n_fr_chorus_ubl-8.0.1.0.0.99.dev3.dist-info/RECORD
odoo8_addon_l10n_fr_chorus_ubl-8.0.1.0.0.99.dev3.dist-info/WHEEL
odoo8_addon_l10n_fr_chorus_ubl-8.0.1.0.0.99.dev3.dist-info/namespace_packages.txt
odoo8_addon_l10n_fr_chorus_ubl-8.0.1.0.0.99.dev3.dist-info/top_level.txt
odoo_addons/l10n_fr_chorus_ubl/README.rst
odoo_addons/l10n_fr_chorus_ubl/__init__.py
odoo_addons/l10n_fr_chorus_ubl/__openerp__.py
odoo_addons/l10n_fr_chorus_ubl/i18n/l10n_fr_chorus_ubl.pot
odoo_addons/l10n_fr_chorus_ubl/models/__init__.py
odoo_addons/l10n_fr_chorus_ubl/models/account_invoice.py
odoo_addons/l10n_fr_chorus_ubl/models/ubl.py
odoo_addons/l10n_fr_chorus_ubl/static/description/icon.png
odoo_addons/l10n_fr_chorus_ubl/tests/__init__.py
odoo_addons/l10n_fr_chorus_ubl/tests/test_chorus_ubl.py
